.editorconfig
.gitignore
.pre-commit-config.yaml
ACKNOWLEDGEMENTS.md
CHANGELOG.md
CONTRIBUTING.md
LICENSE
MANIFEST.in
README.rst
pyproject.toml
setup.cfg
setup.py
tox.ini
.github/workflows/release.yml
.github/workflows/test.yml
django_push_notifications_odil.egg-info/PKG-INFO
django_push_notifications_odil.egg-info/SOURCES.txt
django_push_notifications_odil.egg-info/dependency_links.txt
django_push_notifications_odil.egg-info/requires.txt
django_push_notifications_odil.egg-info/top_level.txt
docs/APNS.rst
push_notifications/__init__.py
push_notifications/admin.py
push_notifications/apns.py
push_notifications/compat.py
push_notifications/exceptions.py
push_notifications/fields.py
push_notifications/gcm.py
push_notifications/models.py
push_notifications/settings.py
push_notifications/webpush.py
push_notifications/wns.py
push_notifications/api/__init__.py
push_notifications/api/rest_framework.py
push_notifications/conf/__init__.py
push_notifications/conf/app.py
push_notifications/conf/appmodel.py
push_notifications/conf/base.py
push_notifications/conf/legacy.py
push_notifications/migrations/0001_initial.py
push_notifications/migrations/0002_auto_20160106_0850.py
push_notifications/migrations/0003_wnsdevice.py
push_notifications/migrations/0004_fcm.py
push_notifications/migrations/0005_applicationid.py
push_notifications/migrations/0006_webpushdevice.py
push_notifications/migrations/0007_uniquesetting.py
push_notifications/migrations/__init__.py
tests/__init__.py
tests/responses.py
tests/settings.py
tests/settings_unique.py
tests/test_apns_models.py
tests/test_apns_push_payload.py
tests/test_app_config.py
tests/test_gcm_push_payload.py
tests/test_legacy_config.py
tests/test_models.py
tests/test_rest_framework.py
tests/test_wns.py
tests/tst_unique.py
tests/test_data/good_revoked.pem
tests/test_data/good_with_passwd.pem
tests/test_data/without_private.pem