Metadata-Version: 2.1
Name: django-push-notifications-odil
Version: 0.1.dev4
Summary: Send push notifications to mobile devices through GCM, APNS or WNS and to WebPush (Chrome, Firefox and Opera) in Django
Home-page: https://github.com/asman84/django-push-notifications-odil
Author: Jerome Leclanche
Author-email: jerome@leclan.ch
License: UNKNOWN
Download-URL: https://github.com/asman84/django-push-notifications-odil/archive/refs/tags/v_02.tar.gz
Platform: UNKNOWN
Classifier: Development Status :: 5 - Production/Stable
Classifier: Environment :: Web Environment
Classifier: Framework :: Django
Classifier: Framework :: Django :: 2.2
Classifier: Framework :: Django :: 3.0
Classifier: Framework :: Django :: 3.1
Classifier: Intended Audience :: Developers
Classifier: License :: OSI Approved :: MIT License
Classifier: Programming Language :: Python
Classifier: Programming Language :: Python :: 3
Classifier: Programming Language :: Python :: 3.6
Classifier: Programming Language :: Python :: 3.7
Classifier: Programming Language :: Python :: 3.8
Classifier: Programming Language :: Python :: 3.9
Classifier: Topic :: Internet :: WWW/HTTP
Classifier: Topic :: System :: Networking
Requires-Python: >=3.6
Provides-Extra: apns
Provides-Extra: wp
